chempp/__init__.py
chempp/crawler.py
chempp/article/__init__.py
chempp/article/article.py
chempp/article/figure.py
chempp/article/paragraph.py
chempp/article/table.py
chempp/constr/__init__.py
chempp/constr/article_constr.py
chempp/constr/section_extr.py
chempp/utils/__init__.py
chempp/utils/macro.py
chempp/utils/utils.py
ChemistryPaperParser-0.1.1.dist-info/LICENSE
ChemistryPaperParser-0.1.1.dist-info/METADATA
ChemistryPaperParser-0.1.1.dist-info/WHEEL
ChemistryPaperParser-0.1.1.dist-info/top_level.txt
ChemistryPaperParser-0.1.1.dist-info/RECORD
