Metadata-Version: 2.1
Name: ChemistryPaperParser
Version: 0.1.1
Summary: Parsing HTML chemistry papers from certain publishers into plain text
Home-page: https://github.com/Yinghao-Li/ChemistryHTMLPaperParser
Author: Yinghao Li
Author-email: yinghaoli@gatech.edu
License: MIT
Keywords: data-mining natural-language-processing nlp parser chemistry
Classifier: Intended Audience :: Developers
Classifier: Intended Audience :: Science/Research
Classifier: License :: OSI Approved :: MIT License
Classifier: Operating System :: OS Independent
Classifier: Programming Language :: Python :: 3
Classifier: Topic :: Scientific/Engineering :: Chemistry
Classifier: Topic :: Scientific/Engineering :: Information Analysis
Requires-Python: >=3.9
License-File: LICENSE
